image_processing_ru4n/__init__.py
image_processing_ru4n/processing/__init__.py
image_processing_ru4n/processing/combination.py
image_processing_ru4n/processing/transformation.py
image_processing_ru4n/utils/__init__.py
image_processing_ru4n/utils/io.py
image_processing_ru4n/utils/plot.py
image_processing_ru4n-0.0.1.dist-info/METADATA
image_processing_ru4n-0.0.1.dist-info/WHEEL
image_processing_ru4n-0.0.1.dist-info/top_level.txt
image_processing_ru4n-0.0.1.dist-info/RECORD
