Metadata-Version: 2.1
Name: image-processing-ru4n
Version: 0.0.1
Summary: Image processing package using skimage
Home-page: https://github.com/Ru4nC/image-processing-package
Author: Ruan
Requires-Python: >=3.8
Requires-Dist: matplotlib
Requires-Dist: numpy
Requires-Dist: scikit-image>=0.16.1
